{
    "Battleaxe": {
        "name": "Battleaxe",
        "desc": "",
        "weapon_category": "MARTIAL",
        "weapon_type": "MELEE",
        "damage_die": 8,
        "num_die": 1,
        "bonus_damage": 0,
        "damage_type": "SLASHING",
        "weapon_range": [
            5,
            5
        ],
        "hit_bonus": 0,
        "weight": 4.0,
        "weight_category": "NONE",
        "two_handed": false,
        "finesse": false,
        "thrown": false,
        "loading": false,
        "ammunition": false,
        "item_type": "WEAPON"
    },
    "Greataxe": {
        "name": "Greataxe",
        "desc": "",
        "weapon_category": "MARTIAL",
        "weapon_type": "MELEE",
        "damage_die": 12,
        "num_die": 1,
        "bonus_damage": 0,
        "damage_type": "SLASHING",
        "weapon_range": [
            5,
            5
        ],
        "hit_bonus": 0,
        "weight": 7.0,
        "weight_category": "HEAVY",
        "two_handed": true,
        "finesse": false,
        "thrown": false,
        "loading": false,
        "ammunition": false,
        "item_type": "WEAPON"
    },
    "Handaxe": {
        "name": "Handaxe",
        "desc": "",
        "weapon_category": "SIMPLE",
        "weapon_type": "MELEE",
        "damage_die": 6,
        "num_die": 1,
        "bonus_damage": 0,
        "damage_type": "SLASHING",
        "weapon_range": [
            20,
            60
        ],
        "hit_bonus": 0,
        "weight": 2.0,
        "weight_category": "HEAVY",
        "two_handed": false,
        "finesse": false,
        "thrown": true,
        "loading": false,
        "ammunition": false,
        "item_type": "WEAPON"
    },
    "Longbow": {
        "name": "Longbow",
        "desc": "",
        "weapon_category": "MARTIAL",
        "weapon_type": "RANGED",
        "damage_die": 8,
        "num_die": 1,
        "bonus_damage": 0,
        "damage_type": "PIERCING",
        "weapon_range": [
            150,
            600
        ],
        "hit_bonus": 0,
        "weight": 2.0,
        "weight_category": "HEAVY",
        "two_handed": true,
        "finesse": false,
        "thrown": false,
        "loading": false,
        "ammunition": true,
        "item_type": "WEAPON"
    },
    "Shortbow": {
        "name": "Shortbow",
        "desc": "",
        "weapon_category": "SIMPLE",
        "weapon_type": "RANGED",
        "damage_die": 6,
        "num_die": 1,
        "bonus_damage": 0,
        "damage_type": "PIERCING",
        "weapon_range": [
            80,
            320
        ],
        "hit_bonus": 0,
        "weight": 2.0,
        "weight_category": "NONE",
        "two_handed": true,
        "finesse": false,
        "thrown": false,
        "loading": false,
        "ammunition": true,
        "item_type": "WEAPON"
    },
    "Club": {
        "name": "Club",
        "desc": "",
        "weapon_category": "SIMPLE",
        "weapon_type": "MELEE",
        "damage_die": 4,
        "num_die": 1,
        "bonus_damage": 0,
        "damage_type": "BLUDGEONING",
        "weapon_range": [
            5,
            5
        ],
        "hit_bonus": 0,
        "weight": 2.0,
        "weight_category": "HEAVY",
        "two_handed": false,
        "finesse": false,
        "thrown": false,
        "loading": false,
        "ammunition": false,
        "item_type": "WEAPON"
    },
    "Greatclub": {
        "name": "Greatclub",
        "desc": "",
        "weapon_category": "SIMPLE",
        "weapon_type": "MELEE",
        "damage_die": 8,
        "num_die": 1,
        "bonus_damage": 0,
        "damage_type": "BLUDGEONING",
        "weapon_range": [
            5,
            5
        ],
        "hit_bonus": 0,
        "weight": 10.0,
        "weight_category": "NONE",
        "two_handed": true,
        "finesse": false,
        "thrown": false,
        "loading": false,
        "ammunition": false,
        "item_type": "WEAPON"
    },
    "Hand Crossbow": {
        "name": "Hand Crossbow",
        "desc": "",
        "weapon_category": "MARTIAL",
        "weapon_type": "RANGED",
        "damage_die": 6,
        "num_die": 1,
        "bonus_damage": 0,
        "damage_type": "PIERCING",
        "weapon_range": [
            30,
            120
        ],
        "hit_bonus": 0,
        "weight": 3.0,
        "weight_category": "HEAVY",
        "two_handed": false,
        "finesse": false,
        "thrown": false,
        "loading": true,
        "ammunition": true,
        "item_type": "WEAPON"
    },
    "Heavy Crossbow": {
        "name": "Heavy Crossbow",
        "desc": "",
        "weapon_category": "MARTIAL",
        "weapon_type": "RANGED",
        "damage_die": 10,
        "num_die": 1,
        "bonus_damage": 0,
        "damage_type": "PIERCING",
        "weapon_range": [
            100,
            400
        ],
        "hit_bonus": 0,
        "weight": 18.0,
        "weight_category": "HEAVY",
        "two_handed": true,
        "finesse": false,
        "thrown": false,
        "loading": true,
        "ammunition": true,
        "item_type": "WEAPON"
    },
    "Light Crossbow": {
        "name": "Light Crossbow",
        "desc": "",
        "weapon_category": "SIMPLE",
        "weapon_type": "RANGED",
        "damage_die": 8,
        "num_die": 1,
        "bonus_damage": 0,
        "damage_type": "PIERCING",
        "weapon_range": [
            80,
            320
        ],
        "hit_bonus": 0,
        "weight": 5.0,
        "weight_category": "NONE",
        "two_handed": true,
        "finesse": false,
        "thrown": false,
        "loading": true,
        "ammunition": true,
        "item_type": "WEAPON"
    },
    "Dagger": {
        "name": "Dagger",
        "desc": "",
        "weapon_category": "SIMPLE",
        "weapon_type": "MELEE",
        "damage_die": 4,
        "num_die": 1,
        "bonus_damage": 0,
        "damage_type": "PIERCING",
        "weapon_range": [
            20,
            60
        ],
        "hit_bonus": 0,
        "weight": 1.0,
        "weight_category": "HEAVY",
        "two_handed": false,
        "finesse": true,
        "thrown": true,
        "loading": false,
        "ammunition": false,
        "item_type": "WEAPON"
    },
    "Dart": {
        "name": "Dart",
        "desc": "",
        "weapon_category": "SIMPLE",
        "weapon_type": "RANGED",
        "damage_die": 4,
        "num_die": 1,
        "bonus_damage": 0,
        "damage_type": "PIERCING",
        "weapon_range": [
            20,
            60
        ],
        "hit_bonus": 0,
        "weight": 0.25,
        "weight_category": "NONE",
        "two_handed": false,
        "finesse": true,
        "thrown": true,
        "loading": false,
        "ammunition": false,
        "item_type": "WEAPON"
    },
    "Flail": {
        "name": "Flail",
        "desc": "",
        "weapon_category": "MARTIAL",
        "weapon_type": "MELEE",
        "damage_die": 8,
        "num_die": 1,
        "bonus_damage": 0,
        "damage_type": "BLUDGEONING",
        "weapon_range": [
            5,
            5
        ],
        "hit_bonus": 0,
        "weight": 2.0,
        "weight_category": "NONE",
        "two_handed": false,
        "finesse": false,
        "thrown": false,
        "loading": false,
        "ammunition": false,
        "item_type": "WEAPON"
    },
    "Glaive": {
        "name": "Glaive",
        "desc": "",
        "weapon_category": "MARTIAL",
        "weapon_type": "MELEE",
        "damage_die": 10,
        "num_die": 1,
        "bonus_damage": 0,
        "damage_type": "SLASHING",
        "weapon_range": [
            5,
            5
        ],
        "hit_bonus": 0,
        "weight": 6.0,
        "weight_category": "HEAVY",
        "two_handed": true,
        "finesse": false,
        "thrown": false,
        "loading": false,
        "ammunition": false,
        "item_type": "WEAPON"
    },
    "Halberd": {
        "name": "Halberd",
        "desc": "",
        "weapon_category": "MARTIAL",
        "weapon_type": "MELEE",
        "damage_die": 10,
        "num_die": 1,
        "bonus_damage": 0,
        "damage_type": "SLASHING",
        "weapon_range": [
            5,
            5
        ],
        "hit_bonus": 0,
        "weight": 6.0,
        "weight_category": "HEAVY",
        "two_handed": true,
        "finesse": false,
        "thrown": false,
        "loading": false,
        "ammunition": false,
        "item_type": "WEAPON"
    },
    "Light Hammer": {
        "name": "Light Hammer",
        "desc": "",
        "weapon_category": "SIMPLE",
        "weapon_type": "MELEE",
        "damage_die": 4,
        "num_die": 1,
        "bonus_damage": 0,
        "damage_type": "BLUDGEONING",
        "weapon_range": [
            20,
            60
        ],
        "hit_bonus": 0,
        "weight": 2.0,
        "weight_category": "HEAVY",
        "two_handed": false,
        "finesse": false,
        "thrown": true,
        "loading": false,
        "ammunition": false,
        "item_type": "WEAPON"
    },
    "Maul": {
        "name": "Maul",
        "desc": "",
        "weapon_category": "MARTIAL",
        "weapon_type": "MELEE",
        "damage_die": 6,
        "num_die": 2,
        "bonus_damage": 0,
        "damage_type": "BLUDGEONING",
        "weapon_range": [
            5,
            5
        ],
        "hit_bonus": 0,
        "weight": 10.0,
        "weight_category": "HEAVY",
        "two_handed": true,
        "finesse": false,
        "thrown": false,
        "loading": false,
        "ammunition": false,
        "item_type": "WEAPON"
    },
    "Warhammer": {
        "name": "Warhammer",
        "desc": "",
        "weapon_category": "MARTIAL",
        "weapon_type": "MELEE",
        "damage_die": 8,
        "num_die": 1,
        "bonus_damage": 0,
        "damage_type": "BLUDGEONING",
        "weapon_range": [
            5,
            5
        ],
        "hit_bonus": 0,
        "weight": 2.0,
        "weight_category": "NONE",
        "two_handed": false,
        "finesse": false,
        "thrown": false,
        "loading": false,
        "ammunition": false,
        "item_type": "WEAPON"
    },
    "Javelin": {
        "name": "Javelin",
        "desc": "",
        "weapon_category": "SIMPLE",
        "weapon_type": "MELEE",
        "damage_die": 6,
        "num_die": 1,
        "bonus_damage": 0,
        "damage_type": "PIERCING",
        "weapon_range": [
            30,
            120
        ],
        "hit_bonus": 0,
        "weight": 2.0,
        "weight_category": "NONE",
        "two_handed": false,
        "finesse": false,
        "thrown": true,
        "loading": false,
        "ammunition": false,
        "item_type": "WEAPON"
    },
    "Lance": {
        "name": "Lance",
        "desc": "",
        "weapon_category": "MARTIAL",
        "weapon_type": "MELEE",
        "damage_die": 12,
        "num_die": 1,
        "bonus_damage": 0,
        "damage_type": "PIERCING",
        "weapon_range": [
            5,
            5
        ],
        "hit_bonus": 0,
        "weight": 6.0,
        "weight_category": "NONE",
        "two_handed": false,
        "finesse": false,
        "thrown": false,
        "loading": false,
        "ammunition": false,
        "item_type": "WEAPON"
    },
    "Mace": {
        "name": "Mace",
        "desc": "",
        "weapon_category": "SIMPLE",
        "weapon_type": "MELEE",
        "damage_die": 6,
        "num_die": 1,
        "bonus_damage": 0,
        "damage_type": "BLUDGEONING",
        "weapon_range": [
            5,
            5
        ],
        "hit_bonus": 0,
        "weight": 4.0,
        "weight_category": "NONE",
        "two_handed": false,
        "finesse": false,
        "thrown": false,
        "loading": false,
        "ammunition": false,
        "item_type": "WEAPON"
    },
    "Morningstar": {
        "name": "Morningstar",
        "desc": "",
        "weapon_category": "MARTIAL",
        "weapon_type": "MELEE",
        "damage_die": 8,
        "num_die": 1,
        "bonus_damage": 0,
        "damage_type": "PIERCING",
        "weapon_range": [
            5,
            5
        ],
        "hit_bonus": 0,
        "weight": 4.0,
        "weight_category": "NONE",
        "two_handed": false,
        "finesse": false,
        "thrown": false,
        "loading": false,
        "ammunition": false,
        "item_type": "WEAPON"
    },
    "Pike": {
        "name": "Pike",
        "desc": "",
        "weapon_category": "MARTIAL",
        "weapon_type": "MELEE",
        "damage_die": 10,
        "num_die": 1,
        "bonus_damage": 0,
        "damage_type": "PIERCING",
        "weapon_range": [
            5,
            5
        ],
        "hit_bonus": 0,
        "weight": 18.0,
        "weight_category": "HEAVY",
        "two_handed": true,
        "finesse": false,
        "thrown": false,
        "loading": false,
        "ammunition": false,
        "item_type": "WEAPON"
    },
    "Quarterstaff": {
        "name": "Quarterstaff",
        "desc": "",
        "weapon_category": "SIMPLE",
        "weapon_type": "MELEE",
        "damage_die": 6,
        "num_die": 1,
        "bonus_damage": 0,
        "damage_type": "BLUDGEONING",
        "weapon_range": [
            5,
            5
        ],
        "hit_bonus": 0,
        "weight": 4.0,
        "weight_category": "NONE",
        "two_handed": false,
        "finesse": false,
        "thrown": false,
        "loading": false,
        "ammunition": false,
        "item_type": "WEAPON"
    },
    "Sickle": {
        "name": "Sickle",
        "desc": "",
        "weapon_category": "SIMPLE",
        "weapon_type": "MELEE",
        "damage_die": 4,
        "num_die": 1,
        "bonus_damage": 0,
        "damage_type": "SLASHING",
        "weapon_range": [
            5,
            5
        ],
        "hit_bonus": 0,
        "weight": 2.0,
        "weight_category": "HEAVY",
        "two_handed": false,
        "finesse": false,
        "thrown": false,
        "loading": false,
        "ammunition": false,
        "item_type": "WEAPON"
    },
    "Sling": {
        "name": "Sling",
        "desc": "",
        "weapon_category": "SIMPLE",
        "weapon_type": "RANGED",
        "damage_die": 4,
        "num_die": 1,
        "bonus_damage": 0,
        "damage_type": "BLUDGEONING",
        "weapon_range": [
            30,
            120
        ],
        "hit_bonus": 0,
        "weight": 0,
        "weight_category": "NONE",
        "two_handed": false,
        "finesse": false,
        "thrown": false,
        "loading": false,
        "ammunition": true,
        "item_type": "WEAPON"
    },
    "Spear": {
        "name": "Spear",
        "desc": "",
        "weapon_category": "SIMPLE",
        "weapon_type": "MELEE",
        "damage_die": 6,
        "num_die": 1,
        "bonus_damage": 0,
        "damage_type": "PIERCING",
        "weapon_range": [
            20,
            60
        ],
        "hit_bonus": 0,
        "weight": 3.0,
        "weight_category": "NONE",
        "two_handed": false,
        "finesse": false,
        "thrown": true,
        "loading": false,
        "ammunition": false,
        "item_type": "WEAPON"
    },
    "Greatsword": {
        "name": "Greatsword",
        "desc": "",
        "weapon_category": "MARTIAL",
        "weapon_type": "MELEE",
        "damage_die": 6,
        "num_die": 2,
        "bonus_damage": 0,
        "damage_type": "SLASHING",
        "weapon_range": [
            5,
            5
        ],
        "hit_bonus": 0,
        "weight": 6.0,
        "weight_category": "HEAVY",
        "two_handed": true,
        "finesse": false,
        "thrown": false,
        "loading": false,
        "ammunition": false,
        "item_type": "WEAPON"
    },
    "Longsword": {
        "name": "Longsword",
        "desc": "",
        "weapon_category": "MARTIAL",
        "weapon_type": "MELEE",
        "damage_die": 8,
        "num_die": 1,
        "bonus_damage": 0,
        "damage_type": "SLASHING",
        "weapon_range": [
            5,
            5
        ],
        "hit_bonus": 0,
        "weight": 3.0,
        "weight_category": "NONE",
        "two_handed": false,
        "finesse": false,
        "thrown": false,
        "loading": false,
        "ammunition": false,
        "item_type": "WEAPON"
    },
    "Rapier": {
        "name": "Rapier",
        "desc": "",
        "weapon_category": "MARTIAL",
        "weapon_type": "MELEE",
        "damage_die": 8,
        "num_die": 1,
        "bonus_damage": 0,
        "damage_type": "PIERCING",
        "weapon_range": [
            5,
            5
        ],
        "hit_bonus": 0,
        "weight": 2.0,
        "weight_category": "NONE",
        "two_handed": false,
        "finesse": true,
        "thrown": false,
        "loading": false,
        "ammunition": false,
        "item_type": "WEAPON"
    },
    "Scimitar": {
        "name": "Scimitar",
        "desc": "",
        "weapon_category": "MARTIAL",
        "weapon_type": "MELEE",
        "damage_die": 6,
        "num_die": 1,
        "bonus_damage": 0,
        "damage_type": "SLASHING",
        "weapon_range": [
            5,
            5
        ],
        "hit_bonus": 0,
        "weight": 3.0,
        "weight_category": "HEAVY",
        "two_handed": false,
        "finesse": true,
        "thrown": false,
        "loading": false,
        "ammunition": false,
        "item_type": "WEAPON"
    },
    "Shortsword": {
        "name": "Shortsword",
        "desc": "",
        "weapon_category": "MARTIAL",
        "weapon_type": "MELEE",
        "damage_die": 6,
        "num_die": 1,
        "bonus_damage": 0,
        "damage_type": "PIERCING",
        "weapon_range": [
            5,
            5
        ],
        "hit_bonus": 0,
        "weight": 2.0,
        "weight_category": "HEAVY",
        "two_handed": false,
        "finesse": true,
        "thrown": false,
        "loading": false,
        "ammunition": false,
        "item_type": "WEAPON"
    },
    "Trident": {
        "name": "Trident",
        "desc": "",
        "weapon_category": "MARTIAL",
        "weapon_type": "MELEE",
        "damage_die": 6,
        "num_die": 1,
        "bonus_damage": 0,
        "damage_type": "PIERCING",
        "weapon_range": [
            20,
            60
        ],
        "hit_bonus": 0,
        "weight": 4.0,
        "weight_category": "NONE",
        "two_handed": false,
        "finesse": false,
        "thrown": true,
        "loading": false,
        "ammunition": false,
        "item_type": "WEAPON"
    },
    "War Pick": {
        "name": "War Pick",
        "desc": "",
        "weapon_category": "MARTIAL",
        "weapon_type": "MELEE",
        "damage_die": 8,
        "num_die": 1,
        "bonus_damage": 0,
        "damage_type": "PIERCING",
        "weapon_range": [
            5,
            5
        ],
        "hit_bonus": 0,
        "weight": 2.0,
        "weight_category": "NONE",
        "two_handed": false,
        "finesse": false,
        "thrown": false,
        "loading": false,
        "ammunition": false,
        "item_type": "WEAPON"
    },
    "Whip": {
        "name": "Whip",
        "desc": "",
        "weapon_category": "MARTIAL",
        "weapon_type": "MELEE",
        "damage_die": 4,
        "num_die": 1,
        "bonus_damage": 0,
        "damage_type": "SLASHING",
        "weapon_range": [
            5,
            5
        ],
        "hit_bonus": 0,
        "weight": 3.0,
        "weight_category": "NONE",
        "two_handed": false,
        "finesse": true,
        "thrown": false,
        "loading": false,
        "ammunition": false,
        "item_type": "WEAPON"
    }
}